easyconf/__init__.py
easyconf/config.py
easyconf/constants.py
easyconf/loader.py
easyconf/random.py
easyconf/url.py
easyconf/generators/__init__.py
easyconf/generators/gitignore.py
easyconf/generators/yaml.py
easyconf-1.3.1.dist-info/METADATA
easyconf-1.3.1.dist-info/WHEEL
easyconf-1.3.1.dist-info/top_level.txt
easyconf-1.3.1.dist-info/RECORD
