Metadata-Version: 2.1
Name: easyconf
Version: 1.3.1
Summary: Easy file-based and environment configuration.
Home-page: https://github.com/lincolnloop/easyconf/
Author: Chris Beaven
Author-email: smileychris@gmail.com
License: MIT
Keywords: configuration
Platform: UNKNOWN
Classifier: Development Status :: 3 - Alpha
Classifier: Intended Audience :: Developers
Classifier: License :: OSI Approved :: MIT License
Classifier: Operating System :: OS Independent
Classifier: Programming Language :: Python
Classifier: Programming Language :: Python :: 3.4
Classifier: Programming Language :: Python :: 3.5
Classifier: Programming Language :: Python :: 3.6
Requires-Dist: django-environ
Requires-Dist: ruamel.yaml (<0.16)
Requires-Dist: gitpython
Provides-Extra: dev
Requires-Dist: pytest ; extra == 'dev'
Requires-Dist: pytest-cov ; extra == 'dev'
Requires-Dist: pytest-mock ; extra == 'dev'
Provides-Extra: maintainer
Requires-Dist: zest.releaser[recommended] ; extra == 'maintainer'
